get_code_from_markdown.py
get_code_from_markdown-1.0.0.dist-info/LICENSE
get_code_from_markdown-1.0.0.dist-info/METADATA
get_code_from_markdown-1.0.0.dist-info/WHEEL
get_code_from_markdown-1.0.0.dist-info/top_level.txt
get_code_from_markdown-1.0.0.dist-info/RECORD
