Metadata-Version: 2.1
Name: get-code-from-markdown
Version: 1.0.0
Summary: extract code from within triple-quotes (```) in markdown files
Author-email: Brianna Rainey <brianna@tassaron.com>
Project-URL: Homepage, https://github.com/tassaron/get_code_from_markdown
Project-URL: Bug Tracker, https://github.com/tassaron/get_code_from_markdown/issues
Classifier: Programming Language :: Python :: 3
Classifier: License :: OSI Approved :: Apache Software License
Classifier: Operating System :: OS Independent
Requires-Python: >=3.9
License-File: LICENSE
